bluprint/__init__.py
bluprint/binary.py
bluprint/cli.py
bluprint/colors.py
bluprint/config.py
bluprint/errors.py
bluprint/index.py
bluprint/project.py
bluprint/template.py
bluprint/create/__init__.py
bluprint/create/errors.py
bluprint/create/py_project.py
bluprint/create/r_project.py
bluprint/template/.gitignore
bluprint/template/README.md
bluprint/template/{{placeholder_name}}.Rproj
bluprint/template/conf/config.yaml
bluprint/template/conf/data.yaml
bluprint/template/data/example_data.csv
bluprint/template/notebooks/example_jupyternb.ipynb
bluprint/template/notebooks/example_quarto.qmd
bluprint/template/notebooks/example_rmarkdown.Rmd
bluprint/template/{{placeholder_name}}/__init__.py
bluprint/template/{{placeholder_name}}/example.py
bluprint-0.4.5.dist-info/METADATA
bluprint-0.4.5.dist-info/WHEEL
bluprint-0.4.5.dist-info/entry_points.txt
bluprint-0.4.5.dist-info/licenses/LICENSE
bluprint-0.4.5.dist-info/RECORD
