Metadata-Version: 2.3
Name: bluprint
Version: 0.4.5
Project-URL: Homepage, https://github.com/igor-sb/bluprint
Project-URL: Issues, https://github.com/igor-sb/bluprint/issues
Author: igor-sb
License: MIT
License-File: LICENSE
Classifier: License :: OSI Approved :: MIT License
Classifier: Operating System :: OS Independent
Classifier: Programming Language :: Python :: 3.11
Classifier: Programming Language :: Python :: 3.12
Requires-Python: >=3.11
Requires-Dist: fire>=0.5.0
Requires-Dist: importlib-resources>=6.1.1
Requires-Dist: omegaconf>=2.3.0
Requires-Dist: packaging>=24.1
